install_process/__init__.py
install_process/install.py
install_process-1.0.post0.dist-info/METADATA
install_process-1.0.post0.dist-info/WHEEL
install_process-1.0.post0.dist-info/licenses/LICENSE
install_process-1.0.post0.dist-info/RECORD
