Metadata-Version: 2.3
Name: install_process
Version: 1.0.post0
Summary: A simple library to help you define your installation process, in Python !
Project-URL: Github, https://github.com/zaicruvoir1rominet/install_process
Project-URL: Changelog, https://github.com/zaicruvoir1rominet/install_process/main/CHANGELOG.md
Project-URL: Documentation, https://install-process.readthedocs.io/en/stable/index.html
License: MIT License
License-File: LICENSE
Classifier: License :: OSI Approved :: MIT License
Classifier: Programming Language :: Python :: 3.9
Classifier: Programming Language :: Python :: 3.10
Classifier: Programming Language :: Python :: 3.11
Classifier: Programming Language :: Python :: 3.12
Classifier: Topic :: Software Development :: Libraries
Requires-Python: >=3.9
Provides-Extra: dev
Requires-Dist: pytest>=8.3.2; extra == 'dev'
Requires-Dist: ruff==0.5.7; extra == 'dev'
Requires-Dist: sphinx; extra == 'dev'
Requires-Dist: sphinx-pyscript; extra == 'dev'
Requires-Dist: sphinx-rtd-theme; extra == 'dev'
Provides-Extra: docs-dep
Requires-Dist: sphinx; extra == 'docs-dep'
Requires-Dist: sphinx-pyscript; extra == 'docs-dep'
Requires-Dist: sphinx-rtd-theme; extra == 'docs-dep'
